{
  "trackers": [
    {
      "type": "unknown",
      "url": "https://media.mediatheques.fr/res/medias/album/400p/262/3416262.jpg"
    },
    {
      "type": "unknown",
      "url": "https://media.mediatheques.fr/res/medias/album/400p/860/3070860.jpg?2"
    },
    {
      "type": "unknown",
      "url": "https://media.mediatheques.fr/res/medias/album/400p/203/645203.jpg"
    },
    {
      "type": "unknown",
      "url": "https://media.mediatheques.fr/res/medias/album/400p/738/4498738.jpg"
    },
    {
      "type": "unknown",
      "url": "https://media.mediatheques.fr/res/medias/album/400p/974/2695974.jpg"
    },
    {
      "type": "unknown",
      "url": "https://media.mediatheques.fr/res/medias/album/400p/473/697473.jpg?2"
    },
    {
      "type": "unknown",
      "url": "https://media.mediatheques.fr/res/medias/album/400p/341/487341.jpg"
    },
    {
      "type": "unknown",
      "url": "https://media.mediatheques.fr/res/medias/album/400p/441/3759441.jpg"
    },
    {
      "type": "unknown",
      "url": "https://media.mediatheques.fr/res/medias/album/400p/649/4495649.jpg"
    },
    {
      "type": "unknown",
      "url": "https://media.mediatheques.fr/res/medias/album/400p/805/4473805.jpg"
    },
    {
      "type": "unknown",
      "url": "https://media.mediatheques.fr/res/medias/album/400p/377/2223377.jpg?2"
    },
    {
      "type": "unknown",
      "url": "https://media.mediatheques.fr/res/medias/album/400p/696/915696.jpg?2"
    },
    {
      "type": "unknown",
      "url": "https://media.mediatheques.fr/res/medias/album/400p/689/4495689.jpg"
    },
    {
      "type": "unknown",
      "url": "https://media.mediatheques.fr/res/medias/album/400p/561/2629561.jpg"
    },
    {
      "type": "unknown",
      "url": "https://media.mediatheques.fr/res/medias/album/400p/812/3283812.jpg"
    },
    {
      "type": "unknown",
      "url": "https://media.mediatheques.fr/res/medias/album/400p/924/1096924.jpg?2"
    },
    {
      "type": "unknown",
      "url": "https://media.mediatheques.fr/res/medias/album/400p/432/872432.jpg"
    },
    {
      "type": "unknown",
      "url": "https://media.mediatheques.fr/res/medias/album/400p/386/2696386.jpg"
    },
    {
      "type": "unknown",
      "url": "https://media.mediatheques.fr/res/medias/album/400p/815/1042815.jpg?2"
    },
    {
      "type": "unknown",
      "url": "https://media.mediatheques.fr/res/medias/album/400p/212/3987212.jpg"
    },
    {
      "type": "unknown",
      "url": "https://media.mediatheques.fr/res/medias/album/400p/331/4324331.jpg?2"
    },
    {
      "type": "unknown",
      "url": "https://media.mediatheques.fr/res/medias/album/400p/105/3679105.jpg"
    },
    {
      "type": "unknown",
      "url": "https://media.mediatheques.fr/res/medias/album/400p/996/912996.jpg?2"
    },
    {
      "type": "unknown",
      "url": "https://media.mediatheques.fr/res/medias/album/400p/317/3459317.jpg"
    },
    {
      "type": "unknown",
      "url": "https://media.mediatheques.fr/res/medias/album/400p/145/4162145.jpg"
    },
    {
      "type": "unknown",
      "url": "https://media.mediatheques.fr/res/medias/album/400p/033/970033.jpg?2"
    },
    {
      "type": "unknown",
      "url": "https://media.mediatheques.fr/res/medias/album/400p/802/4600802.jpg"
    },
    {
      "type": "unknown",
      "url": "https://media.mediatheques.fr/res/medias/album/400p/959/3929959.jpg"
    },
    {
      "type": "unknown",
      "url": "https://media.mediatheques.fr/res/medias/album/400p/429/3124429.jpg"
    },
    {
      "type": "unknown",
      "url": "https://media.mediatheques.fr/res/medias/album/400p/993/1126993.jpg?2"
    },
    {
      "type": "unknown",
      "url": "https://media.mediatheques.fr/res/medias/album/400p/095/1119095.jpg?3"
    },
    {
      "type": "unknown",
      "url": "https://media.mediatheques.fr/res/medias/album/400p/765/4101765.jpg"
    },
    {
      "type": "unknown",
      "url": "https://media.mediatheques.fr/res/medias/album/400p/377/909377.jpg"
    },
    {
      "type": "unknown",
      "url": "https://media.mediatheques.fr/res/medias/album/400p/982/4112982.jpg"
    },
    {
      "type": "unknown",
      "url": "https://media.mediatheques.fr/res/medias/album/400p/191/3022191.jpg?2"
    },
    {
      "type": "unknown",
      "url": "https://media.mediatheques.fr/res/medias/album/400p/979/4112979.jpg?2"
    },
    {
      "type": "unknown",
      "url": "https://media.mediatheques.fr/res/medias/album/400p/624/3730624.jpg"
    },
    {
      "type": "unknown",
      "url": "https://media.mediatheques.fr/res/medias/album/400p/288/4474288.jpg"
    },
    {
      "type": "unknown",
      "url": "https://media.mediatheques.fr/res/medias/album/400p/034/4163034.jpg"
    },
    {
      "type": "unknown",
      "url": "https://media.mediatheques.fr/res/medias/album/400p/117/4146117.jpg"
    },
    {
      "type": "unknown",
      "url": "https://media.mediatheques.fr/res/medias/album/400p/374/3570374.jpg"
    },
    {
      "type": "unknown",
      "url": "https://media.mediatheques.fr/res/medias/album/400p/849/4137849.jpg"
    },
    {
      "type": "unknown",
      "url": "https://media.mediatheques.fr/res/medias/album/400p/473/4171473.jpg"
    },
    {
      "type": "unknown",
      "url": "https://media.mediatheques.fr/res/medias/album/400p/987/4004987.jpg?2"
    },
    {
      "type": "unknown",
      "url": "https://media.mediatheques.fr/res/medias/album/400p/074/3569074.jpg?2"
    },
    {
      "type": "unknown",
      "url": "https://media.mediatheques.fr/res/medias/album/400p/109/3170109.jpg"
    },
    {
      "type": "unknown",
      "url": "https://media.mediatheques.fr/res/medias/album/400p/613/3433613.jpg"
    },
    {
      "type": "unknown",
      "url": "https://media.mediatheques.fr/res/medias/album/400p/694/3047694.jpg"
    },
    {
      "type": "unknown",
      "url": "https://media.mediatheques.fr/res/medias/album/400p/980/4112980.jpg"
    },
    {
      "type": "unknown",
      "url": "https://media.mediatheques.fr/res/medias/album/400p/753/4002753.jpg?3"
    },
    {
      "type": "unknown",
      "url": "https://assets.edenlivres.fr/medias/fa/1b713cb006df16ce0a89a6710bbd7151561c4c.jpg?h=-&w=1000"
    },
    {
      "type": "unknown",
      "url": "https://assets.edenlivres.fr/medias/fa/c97e674336d7c1a5f3a70dd9c9a5ecd943d1ed.jpg?h=-&w=1000"
    },
    {
      "type": "unknown",
      "url": "https://assets.edenlivres.fr/medias/d6/f55d58dc04963ec385423d5f1b1273920008b1.jpg?h=-&w=1000"
    },
    {
      "type": "unknown",
      "url": "https://assets.edenlivres.fr/medias/58/d9f582b68ed520de17afdd10b9ab80e59cb5a1.jpg?h=-&w=1000"
    },
    {
      "type": "unknown",
      "url": "https://couverture.numilog.com/9782700280227_W300.jpg"
    },
    {
      "type": "unknown",
      "url": "https://assets.edenlivres.fr/medias/0b/b0256e4dde1d3e5e7096cecd1745492ebdf084.jpg?h=-&w=1000"
    },
    {
      "type": "unknown",
      "url": "https://assets.edenlivres.fr/medias/f4/73f69996e1cfcba966058dcaa941ac105b97f0.jpg?h=-&w=1000"
    },
    {
      "type": "unknown",
      "url": "https://assets.edenlivres.fr/medias/da/b12effd49b46a28ae8069c419f2d5f15750675.jpg?h=-&w=1000"
    },
    {
      "type": "unknown",
      "url": "https://assets.edenlivres.fr/medias/f0/dfe2d52407008d6979807939ddb459f5d4afa2.jpg?h=-&w=1000"
    },
    {
      "type": "unknown",
      "url": "https://assets.edenlivres.fr/medias/ff/0ab3f748f1ec1bf48d2202bf442a390be4e6ee.jpg?h=-&w=1000"
    },
    {
      "type": "unknown",
      "url": "https://assets.edenlivres.fr/medias/e1/531591df3c1b82279943611df894b5e0c806ae.jpg?h=-&w=1000"
    },
    {
      "type": "unknown",
      "url": "https://assets.edenlivres.fr/medias/0c/22b78c9387f84480df40459eb072561ca66971.jpg?h=-&w=1000"
    },
    {
      "type": "unknown",
      "url": "https://assets.edenlivres.fr/medias/06/0ec5f78bd6db5e670ff587e9b44eb7a1a7852e.jpg?h=-&w=1000"
    },
    {
      "type": "unknown",
      "url": "https://assets.edenlivres.fr/medias/17/ab69f7222b471fccd8065355d3deea04cbba90.jpg?h=-&w=1000"
    },
    {
      "type": "unknown",
      "url": "https://assets.edenlivres.fr/medias/42/a001ae189742d023604ea37d605cd08ec2e29b.jpg?h=-&w=1000"
    },
    {
      "type": "unknown",
      "url": "https://assets.edenlivres.fr/medias/f2/f621587f76f73896e59147511c73fbd9b7ca35.jpg?h=-&w=1000"
    },
    {
      "type": "unknown",
      "url": "https://assets.edenlivres.fr/medias/84/8e27d9feabbf9dc3e4074bfd6e608f56ff9ac8.jpg?h=-&w=1000"
    },
    {
      "type": "cloudfront",
      "url": "https://d1ye1pkjd8d7nc.cloudfront.net/public_item/0001/14/d2f53abfbcd63605a29fa4859a4de2a8fd2050e3.png",
      "details": {
        "id": "cloudfront",
        "message": "Host files locally"
      }
    },
    {
      "type": "cloudfront",
      "url": "https://d1ye1pkjd8d7nc.cloudfront.net/public_item/0001/12/20d28f681a299b242d303a0f3099b9210fad19e2.png",
      "details": {
        "id": "cloudfront",
        "message": "Host files locally"
      }
    },
    {
      "type": "cloudfront",
      "url": "https://d1ye1pkjd8d7nc.cloudfront.net/public_item/0001/14/a7f39455efc49ce5bbe580c4862538ba9f096028.png",
      "details": {
        "id": "cloudfront",
        "message": "Host files locally"
      }
    },
    {
      "type": "cloudfront",
      "url": "https://d1ye1pkjd8d7nc.cloudfront.net/public_item/0001/11/5d479730b5f9bd0dc1842a869ee986837082d0dc.png",
      "details": {
        "id": "cloudfront",
        "message": "Host files locally"
      }
    },
    {
      "type": "cloudfront",
      "url": "https://d1ye1pkjd8d7nc.cloudfront.net/public_item/0001/14/d66fedb201a7db7d2ffa598df864d3f76c3f0c3b.png",
      "details": {
        "id": "cloudfront",
        "message": "Host files locally"
      }
    },
    {
      "type": "cloudfront",
      "url": "https://d1ye1pkjd8d7nc.cloudfront.net/public_item/0001/05/acd1980646ed5d3e139af86aec202e919db8f19d.jpeg",
      "details": {
        "id": "cloudfront",
        "message": "Host files locally"
      }
    },
    {
      "type": "cloudfront",
      "url": "https://d1ye1pkjd8d7nc.cloudfront.net/public_item/0001/12/197f7eb669512b6af0f4a07083d69b7d03912def.jpeg",
      "details": {
        "id": "cloudfront",
        "message": "Host files locally"
      }
    },
    {
      "type": "cloudfront",
      "url": "https://d1ye1pkjd8d7nc.cloudfront.net/public_item/0001/06/6bf6fdcc3cca4c4730be805e8f42f6b770f0fdc8.png",
      "details": {
        "id": "cloudfront",
        "message": "Host files locally"
      }
    },
    {
      "type": "cloudfront",
      "url": "https://d1ye1pkjd8d7nc.cloudfront.net/public_item/0001/12/53fe00370383b85512fbe206048a122da46cc978.png",
      "details": {
        "id": "cloudfront",
        "message": "Host files locally"
      }
    },
    {
      "type": "cloudfront",
      "url": "https://d1ye1pkjd8d7nc.cloudfront.net/public_item/0001/12/1c10ebbc6e5c0cb87c4ed59ababcba8902bd7199.png",
      "details": {
        "id": "cloudfront",
        "message": "Host files locally"
      }
    },
    {
      "type": "cloudfront",
      "url": "https://d1ye1pkjd8d7nc.cloudfront.net/public_item/0001/05/a63a7e22f2af7b1d97aefd89a99665962d8b2e09.jpeg",
      "details": {
        "id": "cloudfront",
        "message": "Host files locally"
      }
    },
    {
      "type": "cloudfront",
      "url": "https://d1ye1pkjd8d7nc.cloudfront.net/public_item/0001/11/9b93bdae856f3b04be8656c022aaac818c44ae73.png",
      "details": {
        "id": "cloudfront",
        "message": "Host files locally"
      }
    },
    {
      "type": "cloudfront",
      "url": "https://d1ye1pkjd8d7nc.cloudfront.net/public_item/0001/14/44e92312a3019c63fec428d9d3d44cadb13b1704.png",
      "details": {
        "id": "cloudfront",
        "message": "Host files locally"
      }
    },
    {
      "type": "cloudfront",
      "url": "https://d1ye1pkjd8d7nc.cloudfront.net/public_item/0001/05/706e22e7540a9da401ad37808e49b17ab44667f1.png",
      "details": {
        "id": "cloudfront",
        "message": "Host files locally"
      }
    },
    {
      "type": "cloudfront",
      "url": "https://d1ye1pkjd8d7nc.cloudfront.net/public_item/0001/14/f99462987f9447c590d5a51aa8645d7f2a0070ef.png",
      "details": {
        "id": "cloudfront",
        "message": "Host files locally"
      }
    },
    {
      "type": "cloudfront",
      "url": "https://d1ye1pkjd8d7nc.cloudfront.net/public_item/0001/13/73262602b420f9f34c45d274db80637c23662415.png",
      "details": {
        "id": "cloudfront",
        "message": "Host files locally"
      }
    },
    {
      "type": "cloudfront",
      "url": "https://d1ye1pkjd8d7nc.cloudfront.net/public_item/0001/14/c0a6bbef44b1d30008efe679b987dbe58b62fc7f.jpeg",
      "details": {
        "id": "cloudfront",
        "message": "Host files locally"
      }
    },
    {
      "type": "cloudfront",
      "url": "https://d1ye1pkjd8d7nc.cloudfront.net/public_item/0001/14/4f2b7c8f1bdb83a53a47592f3a437e5d0c37d48d.png",
      "details": {
        "id": "cloudfront",
        "message": "Host files locally"
      }
    },
    {
      "type": "cloudfront",
      "url": "https://d1ye1pkjd8d7nc.cloudfront.net/public_item/0001/11/82489abe28c6b8d608a158f947e18c98a9fcf92b.png",
      "details": {
        "id": "cloudfront",
        "message": "Host files locally"
      }
    },
    {
      "type": "cloudfront",
      "url": "https://d1ye1pkjd8d7nc.cloudfront.net/public_item/0001/14/7d124c7573a5eb4234d547e28c8699396ab4561e.jpeg",
      "details": {
        "id": "cloudfront",
        "message": "Host files locally"
      }
    },
    {
      "type": "cloudfront",
      "url": "https://d1ye1pkjd8d7nc.cloudfront.net/public_item/0001/14/46649cde7d88557e289a6024dd1a3b52dd8146b5.jpeg",
      "details": {
        "id": "cloudfront",
        "message": "Host files locally"
      }
    },
    {
      "type": "cloudfront",
      "url": "https://d1ye1pkjd8d7nc.cloudfront.net/public_item/0001/09/ab3eb1f34443c14259fe6a0d03af12cc13ec73c7.png",
      "details": {
        "id": "cloudfront",
        "message": "Host files locally"
      }
    },
    {
      "type": "cloudfront",
      "url": "https://d1ye1pkjd8d7nc.cloudfront.net/public_item/0001/12/0921250d398bcac2069dcadabf911fedc84550be.png",
      "details": {
        "id": "cloudfront",
        "message": "Host files locally"
      }
    },
    {
      "type": "cloudfront",
      "url": "https://d1ye1pkjd8d7nc.cloudfront.net/public_item/0001/11/497bfd538edd23dada8f2292bbb33e4c2c349218.png",
      "details": {
        "id": "cloudfront",
        "message": "Host files locally"
      }
    },
    {
      "type": "cloudfront",
      "url": "https://d1ye1pkjd8d7nc.cloudfront.net/public_item/0001/12/8c5bee96c4aab96be1ee21ebc59dc962ff1424be.png",
      "details": {
        "id": "cloudfront",
        "message": "Host files locally"
      }
    },
    {
      "type": "cloudfront",
      "url": "https://d1ye1pkjd8d7nc.cloudfront.net/public_item/0001/11/e2563243c19974aa41934d93d7a4ca621e8d6496.png",
      "details": {
        "id": "cloudfront",
        "message": "Host files locally"
      }
    },
    {
      "type": "cloudfront",
      "url": "https://d1ye1pkjd8d7nc.cloudfront.net/public_item/0001/05/300742f8254a235d51a9e5e660635de0f7646b59.jpeg",
      "details": {
        "id": "cloudfront",
        "message": "Host files locally"
      }
    },
    {
      "type": "cloudfront",
      "url": "https://d1ye1pkjd8d7nc.cloudfront.net/public_item/0001/05/011c310f58619181f896ad2e7bda7a501ac79299.png",
      "details": {
        "id": "cloudfront",
        "message": "Host files locally"
      }
    },
    {
      "type": "cloudfront",
      "url": "https://d1ye1pkjd8d7nc.cloudfront.net/public_item/0001/11/131b96cc5733225f327a902e44f4f556c66c78a1.png",
      "details": {
        "id": "cloudfront",
        "message": "Host files locally"
      }
    },
    {
      "type": "cloudfront",
      "url": "https://d1ye1pkjd8d7nc.cloudfront.net/public_item/0001/09/6c18980bc492bd33a63a3629619b675a7a73dfeb.png",
      "details": {
        "id": "cloudfront",
        "message": "Host files locally"
      }
    },
    {
      "type": "cloudfront",
      "url": "https://d1ye1pkjd8d7nc.cloudfront.net/public_item/0001/12/f8a2d6185ae1b60eb69cd6145e0656dbef685ac6.png",
      "details": {
        "id": "cloudfront",
        "message": "Host files locally"
      }
    },
    {
      "type": "cloudfront",
      "url": "https://d1ye1pkjd8d7nc.cloudfront.net/public_item/0001/05/e6e97779b8108403e03e607791b2b8bac32ba89e.jpeg",
      "details": {
        "id": "cloudfront",
        "message": "Host files locally"
      }
    },
    {
      "type": "cloudfront",
      "url": "https://d1ye1pkjd8d7nc.cloudfront.net/public_item/0001/11/1519b89dace5aa448b1d354e4b0ead5583c1825b.png",
      "details": {
        "id": "cloudfront",
        "message": "Host files locally"
      }
    },
    {
      "type": "unknown",
      "url": "https://assets.edenlivres.fr/medias/63/81777a119372293fdb9d2c3be7c16cb44a7513.jpg?h=-&w=1000"
    },
    {
      "type": "unknown",
      "url": "https://assets.edenlivres.fr/medias/77/56e8420ed0365a018c4bf00d137a30aaa54bd7.jpg?h=-&w=1000"
    },
    {
      "type": "unknown",
      "url": "https://assets.edenlivres.fr/medias/25/d102c7b635289b621cdfb820a7b6aad4354cbd.jpg?h=-&w=1000"
    },
    {
      "type": "unknown",
      "url": "https://couverture.numilog.com/9791039118088_W300.jpg"
    },
    {
      "type": "unknown",
      "url": "https://assets.edenlivres.fr/medias/18/70875ad741f6d5332a6c588c350c080508dbc4.jpg?h=-&w=1000"
    },
    {
      "type": "unknown",
      "url": "https://assets.edenlivres.fr/medias/e5/f878693332a6d6bea1f425fb7ee22e0d1ef895.jpg?h=-&w=1000"
    },
    {
      "type": "unknown",
      "url": "https://assets.edenlivres.fr/medias/a3/5bd5700786a9042382e84b2164f140d180ecbc.jpg?h=-&w=1000"
    },
    {
      "type": "unknown",
      "url": "https://assets.edenlivres.fr/medias/0b/104f7ed6878c4f2035470f32f5f897ad36e431.jpg?h=-&w=1000"
    },
    {
      "type": "unknown",
      "url": "https://assets.edenlivres.fr/medias/57/db7493030547741e38bb7c1b8c56070844a67f.jpg?h=-&w=1000"
    },
    {
      "type": "unknown",
      "url": "https://assets.edenlivres.fr/medias/8a/00673b85855c2cfe6d8928ead3a07f74fbac04.jpg?h=-&w=1000"
    },
    {
      "type": "unknown",
      "url": "https://assets.edenlivres.fr/medias/ed/a33a57a12782d671296c044fefab133871a31a.png?h=-&w=1000"
    },
    {
      "type": "unknown",
      "url": "https://assets.edenlivres.fr/medias/0d/6832ad61cf92a89fa64cdc73a01c91231fd783.jpg?h=-&w=1000"
    },
    {
      "type": "unknown",
      "url": "https://assets.edenlivres.fr/medias/59/cb9d025107ad27bb2193ecc5f2d04b89a70e0c.jpg?h=-&w=1000"
    },
    {
      "type": "unknown",
      "url": "https://assets.edenlivres.fr/medias/0a/9ff2db7fcca2bcdc5e9799183365624da26493.jpg?h=-&w=1000"
    },
    {
      "type": "unknown",
      "url": "https://assets.edenlivres.fr/medias/67/b156fc16f844e786d33e090de8a88010fed40b.jpg?h=-&w=1000"
    },
    {
      "type": "unknown",
      "url": "https://assets.edenlivres.fr/medias/70/8a390d280e0b6a3c1df46a029f59c644d6b0af.jpg?h=-&w=1000"
    },
    {
      "type": "unknown",
      "url": "https://assets.edenlivres.fr/medias/f2/4795c7c0f33ec80e9eb384c266708b2af0a2c4.jpg?h=-&w=1000"
    },
    {
      "type": "unknown",
      "url": "https://assets.edenlivres.fr/medias/cd/6b28e2d5bee4155bc958c9a38f975ec0015a63.jpg?h=-&w=1000"
    },
    {
      "type": "unknown",
      "url": "https://assets.edenlivres.fr/medias/12/ff879edd0869f8b7c225c7f84108ab998cd53d.jpg?h=-&w=1000"
    },
    {
      "type": "unknown",
      "url": "https://assets.edenlivres.fr/medias/c4/51f96a5a67e6b4aa3c939177602bb4adc0030a.jpg?h=-&w=1000"
    },
    {
      "type": "unknown",
      "url": "https://assets.edenlivres.fr/medias/d1/a2fdc2a17446933d7b0efb55ce3002e6dc70e5.jpg?h=-&w=1000"
    },
    {
      "type": "unknown",
      "url": "https://assets.edenlivres.fr/medias/57/badf6342824ac6609c55c91acd16bfc960411e.jpg?h=-&w=1000"
    },
    {
      "type": "unknown",
      "url": "https://assets.edenlivres.fr/medias/3e/b507e76a050a308939e388b369ee8aa26769ca.png?h=-&w=1000"
    },
    {
      "type": "unknown",
      "url": "https://assets.edenlivres.fr/medias/f2/152a270c9abec32d9db4a0d72162bb105f7435.jpg?h=-&w=1000"
    },
    {
      "type": "unknown",
      "url": "https://assets.edenlivres.fr/medias/1f/7c64e7d8ead4d275e548dcd6df6aa9be642a73.jpg?h=-&w=1000"
    },
    {
      "type": "unknown",
      "url": "https://assets.edenlivres.fr/medias/f4/051831b2b4a67e004c91391993ef60b9707bbf.jpg?h=-&w=1000"
    },
    {
      "type": "unknown",
      "url": "https://assets.edenlivres.fr/medias/3e/b91b9b734f2a1768c9151933417f2353148a48.jpg?h=-&w=1000"
    },
    {
      "type": "unknown",
      "url": "https://assets.edenlivres.fr/medias/55/5268b19cc940acaeac9e30605491975d64650b.jpg?h=-&w=1000"
    },
    {
      "type": "unknown",
      "url": "https://assets.edenlivres.fr/medias/1e/e95bf1b8d354bda3dec217fdb52e68e67c104a.jpg?h=-&w=1000"
    },
    {
      "type": "unknown",
      "url": "https://assets.edenlivres.fr/medias/2d/e3cd923a6becddae109eb048f52978e145ea46.png?h=-&w=1000"
    },
    {
      "type": "unknown",
      "url": "https://assets.edenlivres.fr/medias/22/26d20a8257c38b19107aa04528f807432d2685.png?h=-&w=1000"
    },
    {
      "type": "unknown",
      "url": "https://assets.edenlivres.fr/medias/c5/df7b1551ee3feaa39d16464b01f3de3de7730c.jpg?h=-&w=1000"
    },
    {
      "type": "unknown",
      "url": "https://assets.edenlivres.fr/medias/3b/b8e48c338f32899a7755db4a8ffee98852cdc4.jpg?h=-&w=1000"
    },
    {
      "type": "unknown",
      "url": "https://assets.edenlivres.fr/medias/ff/8b54633cb2c0bb84b877cbd60037e187db2b55.jpg?h=-&w=1000"
    },
    {
      "type": "unknown",
      "url": "https://assets.edenlivres.fr/medias/e1/4e6a8f8dd52e4f111446ddb8826411d97c52a3.jpg?h=-&w=1000"
    },
    {
      "type": "unknown",
      "url": "https://assets.edenlivres.fr/medias/e0/c3070b3d0399bfc801a3699992d432e97c0819.jpg?h=-&w=1000"
    },
    {
      "type": "unknown",
      "url": "https://assets.edenlivres.fr/medias/a7/57b62bd1b859d660a18904b46a8737d9c9377c.jpg?h=-&w=1000"
    },
    {
      "type": "unknown",
      "url": "https://statistique.lavienne86.fr/matomo.js"
    },
    {
      "type": "unknown",
      "url": "https://statistique.lavienne86.fr/matomo.php?action_name=Page%20d%27accueil%20-%20Lire%20en%20Vienne%20Coll%C3%A8ges&idsite=19&rec=1&r=295427&h=15&m=49&s=58&url=https%3A%2F%2Flireenviennecolleges.fr%2F&_id=b5de3bed89d31147&_idn=1&send_image=0&_refts=0&pv_id=ONuQjc&pf_net=295&pf_srv=2024&pf_tfr=276&pf_dm1=1909&uadata=%7B%22fullVersionList%22%3A%5B%5D%2C%22mobile%22%3Afalse%2C%22model%22%3A%22%22%2C%22platform%22%3A%22%22%2C%22platformVersion%22%3A%22%22%7D&cookie=1&res=800x600"
    },
    {
      "type": "unknown",
      "url": "https://assets.edenlivres.fr/medias/b8/e5abe8174aa78f6528857cba58f3fdc0a6b383.jpg?h=-&w=1000"
    },
    {
      "type": "unknown",
      "url": "https://assets.cantook.net/medias/d8/ca3765a2717bfc2c25801b1020c9b6bf3d80d1.jpg?h=-&w=1000"
    },
    {
      "type": "unknown",
      "url": "https://assets.edenlivres.fr/medias/b4/31ffe17409d16e56d1ade913512d1b6496425c.jpg?h=-&w=1000"
    },
    {
      "type": "unknown",
      "url": "https://couverture.numilog.com/9791036302947_W300.jpg"
    },
    {
      "type": "unknown",
      "url": "https://assets.edenlivres.fr/medias/92/d0b301c69e582a687ef39bbdb195b7039582fa.jpg?h=-&w=1000"
    },
    {
      "type": "unknown",
      "url": "https://assets.edenlivres.fr/medias/50/736c539c40e53b4de2ed4067e2a7f803680d6b.jpg?h=-&w=1000"
    },
    {
      "type": "unknown",
      "url": "https://couverture.numilog.com/9782226455819_W300.jpg"
    },
    {
      "type": "unknown",
      "url": "https://assets.edenlivres.fr/medias/2f/0d48c05cb6c4be972185924d440adb22a9164a.jpg?h=-&w=1000"
    },
    {
      "type": "unknown",
      "url": "https://assets.edenlivres.fr/medias/d7/7cde0e8ab03bb62d1152bf0709ef2238606879.jpg?h=-&w=1000"
    },
    {
      "type": "unknown",
      "url": "https://assets.edenlivres.fr/medias/aa/e00271278ad5a561067fbf82e5950c8afcb0e5.jpg?h=-&w=1000"
    },
    {
      "type": "unknown",
      "url": "https://couverture.numilog.com/9782278091805_W300.jpg"
    },
    {
      "type": "unknown",
      "url": "https://assets.edenlivres.fr/medias/89/a36fcd07183687dd45179d69319b44a72a6265.jpg?h=-&w=1000"
    },
    {
      "type": "unknown",
      "url": "https://assets.edenlivres.fr/medias/58/44b0c87cc680b467c8cbc1fbccdbf1f15e953f.jpg?h=-&w=1000"
    },
    {
      "type": "unknown",
      "url": "https://assets.edenlivres.fr/medias/41/9c1e3fa8c82eac9f1b23314352d522701e3204.jpg?h=-&w=1000"
    },
    {
      "type": "unknown",
      "url": "https://assets.edenlivres.fr/medias/ab/0288e76ce56fd37da8bca4b200d1acff0583ff.png?h=-&w=1000"
    },
    {
      "type": "unknown",
      "url": "https://couverture.numilog.com/9782747092098_W300.jpg"
    },
    {
      "type": "unknown",
      "url": "https://assets.edenlivres.fr/medias/d0/a3abc44dcc39285f5882e293b2d37811e80dea.jpg?h=-&w=1000"
    },
    {
      "type": "unknown",
      "url": "https://assets.edenlivres.fr/medias/d8/7b61ef0e21026c4dc6b48bc4e1dca8b3a95dad.jpg?h=-&w=1000"
    },
    {
      "type": "unknown",
      "url": "https://assets.cantook.net/medias/66/bc1a8180a4a2f15c3531c6042a028d4e756f5e.jpg?h=-&w=1000"
    },
    {
      "type": "unknown",
      "url": "https://couverture.numilog.com/9782278091836_W300.jpg"
    },
    {
      "type": "unknown",
      "url": "https://assets.edenlivres.fr/medias/b4/cecd28e1ccf0e105b157d91420a766c77fd20c.jpg?h=-&w=1000"
    },
    {
      "type": "unknown",
      "url": "https://assets.edenlivres.fr/medias/6d/78ddaece202514cb9fb96671da0aa0f015311d.jpg?h=-&w=1000"
    },
    {
      "type": "unknown",
      "url": "https://assets.edenlivres.fr/medias/2f/44a310b1abbf0b6f1a151cb5e2ccb10593e5be.jpg?h=-&w=1000"
    },
    {
      "type": "unknown",
      "url": "https://assets.edenlivres.fr/medias/be/368a237ba068b0088231c03d4013064ead2478.jpg?h=-&w=1000"
    },
    {
      "type": "unknown",
      "url": "https://assets.edenlivres.fr/medias/e3/f6a971135e426e51a0a79c9e76fc89fb0218af.jpg?h=-&w=1000"
    },
    {
      "type": "unknown",
      "url": "https://assets.edenlivres.fr/medias/ef/b36021957eb65388905fa3523f48b870a5b3b8.jpg?h=-&w=1000"
    },
    {
      "type": "unknown",
      "url": "https://assets.edenlivres.fr/medias/43/dd105058bc9e1e4e2110fc70b0bf1a58974e68.jpg?h=-&w=1000"
    },
    {
      "type": "unknown",
      "url": "https://couverture.numilog.com/9782278120857_W300.jpg"
    },
    {
      "type": "unknown",
      "url": "https://assets.cantook.net/medias/35/6978fcf1302dec20d154a3d1892a1fc6f4569f.jpg?h=-&w=1000"
    },
    {
      "type": "unknown",
      "url": "https://assets.edenlivres.fr/medias/44/4ebca7bf4fefda2a3eb5e9cb80db6dcf71af18.jpg?h=-&w=1000"
    },
    {
      "type": "unknown",
      "url": "https://assets.edenlivres.fr/medias/d2/5d1379b47659078a0fade4be8fe7b873a41a90.jpg?h=-&w=1000"
    },
    {
      "type": "unknown",
      "url": "https://assets.edenlivres.fr/medias/7d/910098f0cc9bb20d4bc45459113d44b148017f.jpg?h=-&w=1000"
    },
    {
      "type": "unknown",
      "url": "https://assets.edenlivres.fr/medias/b6/34cd606e3ec6717897d4b373346e9e0c0aa741.jpg?h=-&w=1000"
    },
    {
      "type": "unknown",
      "url": "https://couverture.numilog.com/9782700281675_W300.jpg"
    },
    {
      "type": "unknown",
      "url": "https://couverture.numilog.com/9782278091690_W300.jpg"
    },
    {
      "type": "unknown",
      "url": "https://assets.edenlivres.fr/medias/b9/9e24676f15320b9d64e5fe74a941722013c12d.jpg?h=-&w=1000"
    },
    {
      "type": "unknown",
      "url": "https://assets.edenlivres.fr/medias/6b/9c67cfbd6201f57cec54f86ae20afb617a235f.jpg?h=-&w=1000"
    }
  ],
  "cookies": [
    {
      "name": "_pk_ses.19.15f9",
      "value": "1",
      "domain": "lireenviennecolleges.fr",
      "path": "/",
      "expires": 1713284398,
      "size": 16,
      "httpOnly": false,
      "secure": false,
      "session": false,
      "sameSite": "Lax",
      "sameParty": false,
      "sourceScheme": "Secure",
      "sourcePort": 443
    },
    {
      "name": "_pk_id.19.15f9",
      "value": "b5de3bed89d31147.1713282599.",
      "domain": "lireenviennecolleges.fr",
      "path": "/",
      "expires": 1747237799,
      "size": 42,
      "httpOnly": false,
      "secure": false,
      "session": false,
      "sameSite": "Lax",
      "sameParty": false,
      "sourceScheme": "Secure",
      "sourcePort": 443
    },
    {
      "name": "ErmesSearch_Default",
      "value": "%7B%22mainScenario%22%3A%22TOUSLESUNIVERS%22%2C%22mainScenarioText%22%3A%22Tous%20les%20univers%22%7D",
      "domain": "lireenviennecolleges.fr",
      "path": "/",
      "expires": -1,
      "size": 120,
      "httpOnly": false,
      "secure": true,
      "session": true,
      "sameSite": "Strict",
      "sameParty": false,
      "sourceScheme": "Secure",
      "sourcePort": 443
    },
    {
      "name": "InstanceTH",
      "value": "CG86LEVCDefault=lireenvienne",
      "domain": "lireenviennecolleges.fr",
      "path": "/",
      "expires": -1,
      "size": 38,
      "httpOnly": true,
      "secure": true,
      "session": true,
      "sameSite": "Strict",
      "sameParty": false,
      "sourceScheme": "Secure",
      "sourcePort": 443
    },
    {
      "name": "_syrSessGuid",
      "value": "c357b55a-31d7-4f29-9f9a-5d86fb6b8a7a",
      "domain": "lireenviennecolleges.fr",
      "path": "/",
      "expires": 1713284394.2765,
      "size": 48,
      "httpOnly": true,
      "secure": true,
      "session": false,
      "sameSite": "Lax",
      "sameParty": false,
      "sourceScheme": "Secure",
      "sourcePort": 443
    }
  ],
  "headers": {
    "cache-control": "no-cache, no-store",
    "connection": "Keep-Alive",
    "content-encoding": "gzip",
    "content-length": "52701",
    "content-security-policy": "default-src 'self' https: blob: 'unsafe-eval' 'unsafe-inline'; object-src 'none'; style-src https: 'self' 'unsafe-inline'; img-src https: 'self' data: blob:; font-src 'self' data: https:; frame-src 'self' https:; frame-ancestors 'self' https:;connect-src 'self' http:",
    "content-type": "text/html; charset=utf-8",
    "date": "Tue, 16 Apr 2024 15:49:56 GMT",
    "expires": "-1",
    "keep-alive": "timeout=5, max=500",
    "pragma": "no-cache",
    "referrer-policy": "strict-origin-when-cross-origin",
    "server": "Apache",
    "set-cookie": "_syrSessGuid=c357b55a-31d7-4f29-9f9a-5d86fb6b8a7a; expires=Tue, 16-Apr-2024 16:19:54 GMT; path=/; secure; HttpOnly; SameSite=Lax\nInstanceTH=CG86LEVCDefault=lireenvienne; path=/; secure; HttpOnly; SameSite=Strict",
    "strict-transport-security": "max-age=63072000; includeSubDomains; preload",
    "vary": "Accept-Encoding",
    "x-content-type-options": "nosniff",
    "x-xss-protection": "1; mode=block"
  },
  "endpoints": [
    {
      "hostname": "lireenviennecolleges.fr",
      "ip": "83.206.130.186",
      "geoip": {
        "city": {
          "geoname_id": 3031815,
          "names": {
            "de": "Bondy",
            "en": "Bondy",
            "fr": "Bondy",
            "ja": "ボンディ",
            "ru": "Бонди",
            "zh-CN": "邦迪"
          }
        },
        "continent": {
          "code": "EU",
          "geoname_id": 6255148,
          "names": {
            "de": "Europa",
            "en": "Europe",
            "es": "Europa",
            "fr": "Europe",
            "ja": "ヨーロッパ",
            "pt-BR": "Europa",
            "ru": "Европа",
            "zh-CN": "欧洲"
          }
        },
        "country": {
          "geoname_id": 3017382,
          "is_in_european_union": true,
          "iso_code": "FR",
          "names": {
            "de": "Frankreich",
            "en": "France",
            "es": "Francia",
            "fr": "France",
            "ja": "フランス共和国",
            "pt-BR": "França",
            "ru": "Франция",
            "zh-CN": "法国"
          }
        },
        "location": {
          "accuracy_radius": 200,
          "latitude": 48.9043,
          "longitude": 2.4877,
          "time_zone": "Europe/Paris"
        },
        "postal": {
          "code": "93140"
        },
        "registered_country": {
          "geoname_id": 3017382,
          "is_in_european_union": true,
          "iso_code": "FR",
          "names": {
            "de": "Frankreich",
            "en": "France",
            "es": "Francia",
            "fr": "France",
            "ja": "フランス共和国",
            "pt-BR": "França",
            "ru": "Франция",
            "zh-CN": "法国"
          }
        },
        "subdivisions": [
          {
            "geoname_id": 3012874,
            "iso_code": "IDF",
            "names": {
              "de": "Île-de-France",
              "en": "Île-de-France",
              "es": "Isla de Francia",
              "fr": "Île-de-France",
              "ja": "イル・ド・フランス",
              "pt-BR": "Ilha de França",
              "ru": "Иль-де-Франс",
              "zh-CN": "法兰西岛"
            }
          },
          {
            "geoname_id": 2975246,
            "iso_code": "93",
            "names": {
              "de": "Seine-Saint-Denis",
              "en": "Seine-Saint-Denis",
              "es": "Sena Saint Denis",
              "fr": "Seine-Saint-Denis",
              "ja": "セーヌ＝サン＝ドニ県",
              "pt-BR": "Seine-Saint-Denis",
              "ru": "Сен-Сен-Дени",
              "zh-CN": "塞纳-圣但尼省"
            }
          }
        ]
      }
    },
    {
      "hostname": "media.mediatheques.fr",
      "ip": "5.196.212.149",
      "geoip": {
        "continent": {
          "code": "EU",
          "geoname_id": 6255148,
          "names": {
            "de": "Europa",
            "en": "Europe",
            "es": "Europa",
            "fr": "Europe",
            "ja": "ヨーロッパ",
            "pt-BR": "Europa",
            "ru": "Европа",
            "zh-CN": "欧洲"
          }
        },
        "country": {
          "geoname_id": 3017382,
          "is_in_european_union": true,
          "iso_code": "FR",
          "names": {
            "de": "Frankreich",
            "en": "France",
            "es": "Francia",
            "fr": "France",
            "ja": "フランス共和国",
            "pt-BR": "França",
            "ru": "Франция",
            "zh-CN": "法国"
          }
        },
        "location": {
          "accuracy_radius": 1000,
          "latitude": 48.8582,
          "longitude": 2.3387,
          "time_zone": "Europe/Paris"
        },
        "registered_country": {
          "geoname_id": 3017382,
          "is_in_european_union": true,
          "iso_code": "FR",
          "names": {
            "de": "Frankreich",
            "en": "France",
            "es": "Francia",
            "fr": "France",
            "ja": "フランス共和国",
            "pt-BR": "França",
            "ru": "Франция",
            "zh-CN": "法国"
          }
        }
      }
    },
    {
      "hostname": "assets.edenlivres.fr",
      "ip": "34.95.8.150",
      "geoip": {
        "city": {
          "geoname_id": 6077243,
          "names": {
            "de": "Montreal",
            "en": "Montreal",
            "es": "Montreal",
            "fr": "Montréal",
            "ja": "モントリオール",
            "pt-BR": "Montreal",
            "ru": "Монреаль",
            "zh-CN": "蒙特利尔"
          }
        },
        "continent": {
          "code": "NA",
          "geoname_id": 6255149,
          "names": {
            "de": "Nordamerika",
            "en": "North America",
            "es": "Norteamérica",
            "fr": "Amérique du Nord",
            "ja": "北アメリカ",
            "pt-BR": "América do Norte",
            "ru": "Северная Америка",
            "zh-CN": "北美洲"
          }
        },
        "country": {
          "geoname_id": 6251999,
          "iso_code": "CA",
          "names": {
            "de": "Kanada",
            "en": "Canada",
            "es": "Canadá",
            "fr": "Canada",
            "ja": "カナダ",
            "pt-BR": "Canadá",
            "ru": "Канада",
            "zh-CN": "加拿大"
          }
        },
        "location": {
          "accuracy_radius": 20,
          "latitude": 45.5075,
          "longitude": -73.5887,
          "time_zone": "America/Toronto"
        },
        "postal": {
          "code": "H3H"
        },
        "registered_country": {
          "geoname_id": 6252001,
          "iso_code": "US",
          "names": {
            "de": "USA",
            "en": "United States",
            "es": "Estados Unidos",
            "fr": "États Unis",
            "ja": "アメリカ",
            "pt-BR": "EUA",
            "ru": "США",
            "zh-CN": "美国"
          }
        },
        "subdivisions": [
          {
            "geoname_id": 6115047,
            "iso_code": "QC",
            "names": {
              "en": "Quebec",
              "fr": "Québec",
              "pt-BR": "Quebeque"
            }
          }
        ]
      }
    },
    {
      "hostname": "couverture.numilog.com",
      "ip": "81.93.2.116",
      "geoip": {
        "city": {
          "geoname_id": 2973675,
          "names": {
            "de": "Suresnes",
            "en": "Suresnes",
            "es": "Suresnes",
            "fr": "Suresnes",
            "ja": "シュレンヌ",
            "ru": "Сюрен"
          }
        },
        "continent": {
          "code": "EU",
          "geoname_id": 6255148,
          "names": {
            "de": "Europa",
            "en": "Europe",
            "es": "Europa",
            "fr": "Europe",
            "ja": "ヨーロッパ",
            "pt-BR": "Europa",
            "ru": "Европа",
            "zh-CN": "欧洲"
          }
        },
        "country": {
          "geoname_id": 3017382,
          "is_in_european_union": true,
          "iso_code": "FR",
          "names": {
            "de": "Frankreich",
            "en": "France",
            "es": "Francia",
            "fr": "France",
            "ja": "フランス共和国",
            "pt-BR": "França",
            "ru": "Франция",
            "zh-CN": "法国"
          }
        },
        "location": {
          "accuracy_radius": 10,
          "latitude": 48.8693,
          "longitude": 2.2313,
          "time_zone": "Europe/Paris"
        },
        "postal": {
          "code": "92150"
        },
        "registered_country": {
          "geoname_id": 3017382,
          "is_in_european_union": true,
          "iso_code": "FR",
          "names": {
            "de": "Frankreich",
            "en": "France",
            "es": "Francia",
            "fr": "France",
            "ja": "フランス共和国",
            "pt-BR": "França",
            "ru": "Франция",
            "zh-CN": "法国"
          }
        },
        "subdivisions": [
          {
            "geoname_id": 3012874,
            "iso_code": "IDF",
            "names": {
              "de": "Île-de-France",
              "en": "Île-de-France",
              "es": "Isla de Francia",
              "fr": "Île-de-France",
              "ja": "イル・ド・フランス",
              "pt-BR": "Ilha de França",
              "ru": "Иль-де-Франс",
              "zh-CN": "法兰西岛"
            }
          },
          {
            "geoname_id": 3013657,
            "iso_code": "92",
            "names": {
              "de": "Hauts-de-Seine",
              "en": "Hauts-de-Seine",
              "es": "Altos de Sena",
              "fr": "Hauts-de-Seine",
              "ja": "オー＝ド＝セーヌ県",
              "pt-BR": "Altos do Sena",
              "ru": "О-де-Сен",
              "zh-CN": "上塞纳省"
            }
          }
        ]
      }
    },
    {
      "hostname": "d1ye1pkjd8d7nc.cloudfront.net",
      "ip": "18.160.0.204",
      "geoip": {
        "continent": {
          "code": "NA",
          "geoname_id": 6255149,
          "names": {
            "de": "Nordamerika",
            "en": "North America",
            "es": "Norteamérica",
            "fr": "Amérique du Nord",
            "ja": "北アメリカ",
            "pt-BR": "América do Norte",
            "ru": "Северная Америка",
            "zh-CN": "北美洲"
          }
        },
        "country": {
          "geoname_id": 6252001,
          "iso_code": "US",
          "names": {
            "de": "USA",
            "en": "United States",
            "es": "Estados Unidos",
            "fr": "États Unis",
            "ja": "アメリカ",
            "pt-BR": "EUA",
            "ru": "США",
            "zh-CN": "美国"
          }
        },
        "location": {
          "accuracy_radius": 1000,
          "latitude": 37.751,
          "longitude": -97.822,
          "time_zone": "America/Chicago"
        },
        "registered_country": {
          "geoname_id": 6252001,
          "iso_code": "US",
          "names": {
            "de": "USA",
            "en": "United States",
            "es": "Estados Unidos",
            "fr": "États Unis",
            "ja": "アメリカ",
            "pt-BR": "EUA",
            "ru": "США",
            "zh-CN": "美国"
          }
        }
      }
    },
    {
      "hostname": "statistique.lavienne86.fr",
      "ip": "87.252.12.208",
      "geoip": {
        "continent": {
          "code": "EU",
          "geoname_id": 6255148,
          "names": {
            "de": "Europa",
            "en": "Europe",
            "es": "Europa",
            "fr": "Europe",
            "ja": "ヨーロッパ",
            "pt-BR": "Europa",
            "ru": "Европа",
            "zh-CN": "欧洲"
          }
        },
        "country": {
          "geoname_id": 3017382,
          "is_in_european_union": true,
          "iso_code": "FR",
          "names": {
            "de": "Frankreich",
            "en": "France",
            "es": "Francia",
            "fr": "France",
            "ja": "フランス共和国",
            "pt-BR": "França",
            "ru": "Франция",
            "zh-CN": "法国"
          }
        },
        "location": {
          "accuracy_radius": 500,
          "latitude": 48.8582,
          "longitude": 2.3387,
          "time_zone": "Europe/Paris"
        },
        "registered_country": {
          "geoname_id": 3017382,
          "is_in_european_union": true,
          "iso_code": "FR",
          "names": {
            "de": "Frankreich",
            "en": "France",
            "es": "Francia",
            "fr": "France",
            "ja": "フランス共和国",
            "pt-BR": "França",
            "ru": "Франция",
            "zh-CN": "法国"
          }
        }
      }
    },
    {
      "hostname": "assets.cantook.net",
      "ip": "34.95.8.150",
      "geoip": {
        "city": {
          "geoname_id": 6077243,
          "names": {
            "de": "Montreal",
            "en": "Montreal",
            "es": "Montreal",
            "fr": "Montréal",
            "ja": "モントリオール",
            "pt-BR": "Montreal",
            "ru": "Монреаль",
            "zh-CN": "蒙特利尔"
          }
        },
        "continent": {
          "code": "NA",
          "geoname_id": 6255149,
          "names": {
            "de": "Nordamerika",
            "en": "North America",
            "es": "Norteamérica",
            "fr": "Amérique du Nord",
            "ja": "北アメリカ",
            "pt-BR": "América do Norte",
            "ru": "Северная Америка",
            "zh-CN": "北美洲"
          }
        },
        "country": {
          "geoname_id": 6251999,
          "iso_code": "CA",
          "names": {
            "de": "Kanada",
            "en": "Canada",
            "es": "Canadá",
            "fr": "Canada",
            "ja": "カナダ",
            "pt-BR": "Canadá",
            "ru": "Канада",
            "zh-CN": "加拿大"
          }
        },
        "location": {
          "accuracy_radius": 20,
          "latitude": 45.5075,
          "longitude": -73.5887,
          "time_zone": "America/Toronto"
        },
        "postal": {
          "code": "H3H"
        },
        "registered_country": {
          "geoname_id": 6252001,
          "iso_code": "US",
          "names": {
            "de": "USA",
            "en": "United States",
            "es": "Estados Unidos",
            "fr": "États Unis",
            "ja": "アメリカ",
            "pt-BR": "EUA",
            "ru": "США",
            "zh-CN": "美国"
          }
        },
        "subdivisions": [
          {
            "geoname_id": 6115047,
            "iso_code": "QC",
            "names": {
              "en": "Quebec",
              "fr": "Québec",
              "pt-BR": "Quebeque"
            }
          }
        ]
      }
    }
  ]
}
